mighty/__init__.py
mighty/action.py
mighty/card.py
mighty/game/__init__.py
mighty/game/common.py
mighty/game/extra.py
mighty/game/play.py
mighty/game/pledge.py
mighty-1.0.1.dist-info/LICENSE
mighty-1.0.1.dist-info/WHEEL
mighty-1.0.1.dist-info/METADATA
mighty-1.0.1.dist-info/RECORD
