Metadata-Version: 2.1
Name: mighty
Version: 1.0.1
Summary: Mighty card game engine
Home-page: https://github.com/dj-shin/mighty-engine
License: MIT
Author: DongJin Shin
Author-email: dongjin.shin.00@gmail.com
Requires-Python: >=3.6,<4.0
Classifier: License :: OSI Approved :: MIT License
Classifier: Programming Language :: Python :: 3
Classifier: Programming Language :: Python :: 3.6
Classifier: Programming Language :: Python :: 3.7
Classifier: Programming Language :: Python :: 3.8
Classifier: Programming Language :: Python :: 3.9
Requires-Dist: pytest (>=6.1.2,<7.0.0)
Project-URL: Repository, https://github.com/dj-shin/mighty-engine
